<?xml version="1.0" encoding="UTF-8"?>
<feature
      id="org.eclipse.ecf.provider.restlet.feature"
      label="ECF Restlet Feature"
      version="1.0.0.qualifier"
      provider-name="Eclipse.org - ECF">

   <description url="http://www.example.com/description">
      [Enter Feature Description here.]
   </description>

   <copyright url="http://www.example.com/copyright">
      [Enter Copyright Description here.]
   </copyright>

   <license url="http://www.example.com/license">
      [Enter License Description here.]
   </license>

   <requires>
      <import feature="org.restlet-osgi" version="2.1.0.snapshotv20111019-2200" match="greaterOrEqual"/>
      <import feature="org.restlet.ext.osgi.servlet.feature" version="0.5.0.201110131235" match="greaterOrEqual"/>
      <import feature="org.restlet.ext.servlet-osgi" version="2.1.0.snapshotv20111019-2200" match="greaterOrEqual"/>
   </requires>

   <plugin
         id="org.eclipse.ecf.provider.restlet"
         download-size="0"
         install-size="0"
         version="0.0.0"
         unpack="false"/>

   <plugin
         id="org.eclipse.ecf.remoteservice.tm.restlet"
         download-size="0"
         install-size="0"
         version="0.0.0"
         unpack="false"/>

</feature>
